MANIFEST.in
README.rst
setup.py
collective/__init__.py
collective.stringinterp.text.egg-info/PKG-INFO
collective.stringinterp.text.egg-info/SOURCES.txt
collective.stringinterp.text.egg-info/dependency_links.txt
collective.stringinterp.text.egg-info/entry_points.txt
collective.stringinterp.text.egg-info/namespace_packages.txt
collective.stringinterp.text.egg-info/not-zip-safe
collective.stringinterp.text.egg-info/requires.txt
collective.stringinterp.text.egg-info/top_level.txt
collective/stringinterp/__init__.py
collective/stringinterp/text/__init__.py
collective/stringinterp/text/adapters.py
collective/stringinterp/text/configure.zcml
collective/stringinterp/text/interfaces.py
collective/stringinterp/text/testing.py
collective/stringinterp/text/locales/plone.pot
collective/stringinterp/text/locales/runi18ndude.sh
collective/stringinterp/text/locales/it/LC_MESSAGES/plone.po
collective/stringinterp/text/tests/__init__.py
collective/stringinterp/text/tests/test_stringinterp.py
collective/stringinterp/text/tests/test_subs_adapters.py
docs/HISTORY.txt
docs/INSTALL.txt
docs/LICENSE.GPL
docs/LICENSE.txt