Metadata-Version: 1.1
Name: collective.stringinterp.text
Version: 0.2
Summary: Additional string interpolation for Plone: add content text in your contentrule e-mail messages
Home-page: http://plone.org/products/collective.stringinterp.text
Author: RedTurtle Technology
Author-email: sviluppoplone@redturtle.it
License: GPL
Keywords: plone plonegov rule interpolation email
Platform: UNKNOWN
Classifier: Development Status :: 4 - Beta
Classifier: Framework :: Plone
Classifier: Framework :: Plone :: 4.0
Classifier: Framework :: Plone :: 4.1
Classifier: Framework :: Plone :: 4.2
Classifier: Framework :: Plone :: 4.3
Classifier: Programming Language :: Python
Classifier: License :: OSI Approved :: GNU General Public License (GPL)
